stat386_project/__init__.py
stat386_project/analysis.py
stat386_project/fetch_data.py
jerm2000_stat_386_project-0.1.4.dist-info/METADATA
jerm2000_stat_386_project-0.1.4.dist-info/WHEEL
jerm2000_stat_386_project-0.1.4.dist-info/top_level.txt
jerm2000_stat_386_project-0.1.4.dist-info/RECORD
