Metadata-Version: 2.4
Name: jerm2000-stat-386-project
Version: 0.1.4
Summary: STAT 386 project package
Author: Jeremy Abbott
Project-URL: Homepage, https://jerm2000.github.io/stat_386_project/
Project-URL: Repository, https://github.com/Jerm2000/stat_386_project
Requires-Python: >=3.10
Requires-Dist: pandas>=2.0
Requires-Dist: matplotlib>=3.8
Requires-Dist: pybaseball>=2.2
Requires-Dist: requests>=2.31
